asknews_sdk/__init__.py
asknews_sdk/client.py
asknews_sdk/errors.py
asknews_sdk/py.typed
asknews_sdk/response.py
asknews_sdk/sdk.py
asknews_sdk/security.py
asknews_sdk/types.py
asknews_sdk/utils.py
asknews_sdk/version.py
asknews_sdk/api/__init__.py
asknews_sdk/api/analytics.py
asknews_sdk/api/base.py
asknews_sdk/api/chat.py
asknews_sdk/api/news.py
asknews_sdk/api/stories.py
asknews_sdk/api/wiki.py
asknews_sdk/dto/__init__.py
asknews_sdk/dto/alert.py
asknews_sdk/dto/base.py
asknews_sdk/dto/chat.py
asknews_sdk/dto/common.py
asknews_sdk/dto/deepnews.py
asknews_sdk/dto/error.py
asknews_sdk/dto/news.py
asknews_sdk/dto/sentiment.py
asknews_sdk/dto/stories.py
asknews_sdk/dto/wiki.py
asknews-0.13.10.dist-info/METADATA
asknews-0.13.10.dist-info/WHEEL
asknews-0.13.10.dist-info/licenses/LICENSE
asknews-0.13.10.dist-info/RECORD
