Metadata-Version: 2.4
Name: asknews
Version: 0.13.10
Summary: Python SDK for AskNews
Project-URL: repository, https://github.com/emergentmethods/asknews-python-sdk
Author-email: Emergent Methods <contact@emergentmethods.ai>
License: MIT
License-File: LICENSE
Classifier: Programming Language :: Python :: 3 :: Only
Classifier: Programming Language :: Python :: 3.8
Classifier: Programming Language :: Python :: 3.9
Classifier: Programming Language :: Python :: 3.10
Classifier: Programming Language :: Python :: 3.11
Classifier: Programming Language :: Python :: 3.12
Classifier: Programming Language :: Python :: 3.13
Requires-Python: >=3.8
Requires-Dist: asgiref>=3.7.2
Requires-Dist: crontab>=1.0.1
Requires-Dist: cryptography<45.0.5,>=40.0.0
Requires-Dist: httpx<0.29.0,>=0.27.2
Requires-Dist: orjson>=3.9.10
Requires-Dist: pydantic[email]>=2.10.4
